AUTHORS.rst
CONTRIBUTING.rst
HISTORY.rst
LICENSE
MANIFEST.in
README.rst
setup.cfg
setup.py
almond/__init__.py
almond/almond.py
almond/cli.py
almond.egg-info/PKG-INFO
almond.egg-info/SOURCES.txt
almond.egg-info/dependency_links.txt
almond.egg-info/entry_points.txt
almond.egg-info/not-zip-safe
almond.egg-info/requires.txt
almond.egg-info/top_level.txt
docs/Makefile
docs/authors.rst
docs/conf.py
docs/contributing.rst
docs/history.rst
docs/index.rst
docs/installation.rst
docs/make.bat
docs/readme.rst
docs/usage.rst
tests/__init__.py
tests/test_almond.py